flask_cli/__init__.py
flask_cli/__main__.py
create_flask_project_cli-0.0.2.dist-info/LICENSE
create_flask_project_cli-0.0.2.dist-info/METADATA
create_flask_project_cli-0.0.2.dist-info/WHEEL
create_flask_project_cli-0.0.2.dist-info/entry_points.txt
create_flask_project_cli-0.0.2.dist-info/top_level.txt
create_flask_project_cli-0.0.2.dist-info/RECORD
