Metadata-Version: 2.1
Name: create-flask-project-cli
Version: 0.0.2
Summary: Create flask project with html and css ready using cli.
Home-page: https://github.com/logan0501/flaskcli.git
Author: Loganathan
Author-email: logan05012001@gmail.com
License: MIT
Keywords: flaskapp cli html css flaskcli
Platform: UNKNOWN
Classifier: Intended Audience :: Developers
Classifier: License :: OSI Approved :: MIT License
Classifier: Programming Language :: Python :: 3
Requires-Dist: requests
Requires-Dist: argparse
